unipi_control_os_helpers/__init__.py
unipi_control_os_helpers/os_tools.py
unipi_control_os_helpers/version.py
unipi_control_os_helpers-2023.1.dist-info/LICENSE
unipi_control_os_helpers-2023.1.dist-info/METADATA
unipi_control_os_helpers-2023.1.dist-info/WHEEL
unipi_control_os_helpers-2023.1.dist-info/entry_points.txt
unipi_control_os_helpers-2023.1.dist-info/top_level.txt
unipi_control_os_helpers-2023.1.dist-info/RECORD
