Metadata-Version: 2.1
Name: unipi-control-os-helpers
Version: 2023.1
Summary: Useful tools for the Unipi Control OS.
Home-page: https://github.com/superbox-dev/unipi-control-os-helpers
Author: Michael Hacker
Author-email: mh@superbox.one
Project-URL: Source Code, https://github.com/superbox-dev/unipi-control-os-helpers
Project-URL: Bug Reports, https://github.com/superbox-dev/unipi-control-os-helpers/issues
Classifier: Development Status :: 5 - Production/Stable
Classifier: License :: OSI Approved :: Apache Software License
Classifier: Programming Language :: Python :: 3
Classifier: Programming Language :: Python :: 3.10
Classifier: Programming Language :: Python :: 3.11
Classifier: Programming Language :: Python :: 3 :: Only
Classifier: Operating System :: POSIX :: Linux
Classifier: Topic :: Utilities
Requires-Python: >=3.10
License-File: LICENSE
Requires-Dist: typer[all] (==0.7.0)
